xgatools/__init__.py
xgatools/config.py
xgatools/general_tools_app.py
xgatools/tool_base.py
xgatools/tool_list.py
xgatools/tool_manager.py
xgatools/dyatona/__init__.py
xgatools/dyatona/expose_tool.py
xgatools/dyatona/files_tool.py
xgatools/dyatona/sandbox_helper.py
xgatools/dyatona/shell_tool.py
xgatools/dyatona/web_search_tool.py
xgatools/non_sandbox/__init__.py
xgatools/non_sandbox/message_tool.py
xgatools/utils/__init__.py
xgatools/utils/files_utils.py
xgatools/utils/setup_env.py
xgatools-0.1.6.dist-info/METADATA
xgatools-0.1.6.dist-info/WHEEL
xgatools-0.1.6.dist-info/entry_points.txt
xgatools-0.1.6.dist-info/RECORD
