Metadata-Version: 2.4
Name: xgatools
Version: 0.1.6
Summary: Extreme General Agent Tools
Requires-Python: >=3.11
Requires-Dist: click==8.2.1
Requires-Dist: colorlog==6.9.0
Requires-Dist: daytona-sdk==0.25.5
Requires-Dist: mcp==1.13.0
Requires-Dist: pyyaml==6.0.2
Requires-Dist: schedule==1.2.2
Requires-Dist: tavily-python==0.7.11
